{
  "configVersion": 1,
  "index": "/Studierendenportal/index.html",
  "assetGroups": [
    {
      "name": "app",
      "installMode": "prefetch",
      "updateMode": "prefetch",
      "urls": [
        "/0.b5f93057015e758d103f.js",
        "/1.557115e0114a24926378.js",
        "/2.10a6b2f51a42ddc22f27.js",
        "/favicon.ico",
        "/index.html",
        "/main.f8d66270641c54501957.js",
        "/polyfills.8a06376160c554ad8e9f.js",
        "/runtime.64edc24e9d60aed030e9.js",
        "/styles.4f4e99a0b9c7836b38db.css"
      ],
      "patterns": [
        "https:\\/\\/fonts\\.googleapis\\.com\\/icon\\?family=Material\\+Icons",
        "https:\\/\\/fonts\\.googleapis\\.com\\/css\\?family=Roboto:300,400,500"
      ]
    },
    {
      "name": "assets",
      "installMode": "lazy",
      "updateMode": "prefetch",
      "urls": [
        "/assets/icons/bus-clock.svg",
        "/assets/icons/home.svg",
        "/assets/icons/icon-128x128.png",
        "/assets/icons/icon-144x144.png",
        "/assets/icons/icon-152x152.png",
        "/assets/icons/icon-192x192.png",
        "/assets/icons/icon-384x384.png",
        "/assets/icons/icon-512x512.png",
        "/assets/icons/icon-72x72.png",
        "/assets/icons/icon-96x96.png",
        "/assets/icons/map-marker.png",
        "/assets/icons/map.svg",
        "/assets/icons/newspaper.svg",
        "/assets/icons/search.svg",
        "/assets/img/Header.jpg"
      ],
      "patterns": []
    }
  ],
  "dataGroups": [
    {
      "name": "news",
      "patterns": [
        "https:\\/\\/www\\.uni-mainz\\.de\\/32\\.php",
        "https:\\/\\/www\\.zdv\\.uni-mainz\\.de\\/feed\\/",
        "https:\\/\\/cors-anywhere\\.herokuapp\\.com\\/https:\\/\\/www\\.uni-mainz\\.de\\/32\\.php",
        "https:\\/\\/cors-anywhere\\.herokuapp\\.com\\/https:\\/\\/www\\.zdv\\.uni-mainz\\.de\\/feed\\/"
      ],
      "strategy": "performance",
      "maxSize": 300,
      "maxAge": 86400000,
      "version": 1
    },
    {
      "name": "building",
      "patterns": [
        "https:\\/\\/raeume\\.uni-mainz\\.de\\/aris-api\\/Building"
      ],
      "strategy": "performance",
      "maxSize": 300,
      "maxAge": 2592000000,
      "version": 1
    }
  ],
  "hashTable": {
    "/0.b5f93057015e758d103f.js": "b343526a35f56ff3ff771c65a2e3fe6854ad2edc",
    "/1.557115e0114a24926378.js": "634e33e9baefa66943d5526d9e68f873bff5a9b7",
    "/2.10a6b2f51a42ddc22f27.js": "48533291f03be3a92117be4e528b6b5e9aa6988a",
    "/assets/icons/bus-clock.svg": "0117de4937c6217a11c8cd288713638f1be420b6",
    "/assets/icons/home.svg": "249e5e3c147ab44dc0227fa7c500956da116da51",
    "/assets/icons/icon-128x128.png": "26d73c548f3b9e4e54eccac4e224708bda67d230",
    "/assets/icons/icon-144x144.png": "7de0294dfeda57ecc20335386f9567c391176029",
    "/assets/icons/icon-152x152.png": "98aad7b3c6420058ae7902925152fd4e21313ae4",
    "/assets/icons/icon-192x192.png": "2748bc0b04e34a4446581c5eef53a84c19c4107a",
    "/assets/icons/icon-384x384.png": "be33c4128fb3ce6482e604218d442fe8b3b97da3",
    "/assets/icons/icon-512x512.png": "be33c4128fb3ce6482e604218d442fe8b3b97da3",
    "/assets/icons/icon-72x72.png": "ed28e41b273c8c59c5411e97be866fc4cca9c5a3",
    "/assets/icons/icon-96x96.png": "8aa0dbee27e672dab66f65158019c9168e02d10e",
    "/assets/icons/map-marker.png": "8887c2171d97e9d47bc797bdef0644b704ec26a4",
    "/assets/icons/map.svg": "591c6a1fe3898353f8b9f7c428d8310d5638580c",
    "/assets/icons/newspaper.svg": "70632603f21a28dc236e8ccf4f9a7ba190aa796d",
    "/assets/icons/search.svg": "1aa53d949e64c1c7dd76f5acd1ada23217a4ea9d",
    "/assets/img/Header.jpg": "f90c23ba3fbf861e9dfa3d9fd034f1d6bf16a2fe",
    "/favicon.ico": "ce6720c2948bc1f64b36d4a547666a2628d51366",
    "/index.html": "58c95f498e5480648e0fc410a0b3118b9a3c8484",
    "/main.f8d66270641c54501957.js": "325f813f728bac73066bc01946f56ed188de5859",
    "/polyfills.8a06376160c554ad8e9f.js": "39897c0921873293ecea8ae9c369cf2557f14cce",
    "/runtime.64edc24e9d60aed030e9.js": "a08803b54e6512bca54d49c4eb5a9fb8ccd02a11",
    "/styles.4f4e99a0b9c7836b38db.css": "24c469c42644112f576d6b2e5eb8e11f25d78512"
  },
  "navigationUrls": [
    {
      "positive": true,
      "regex": "^\\/.*$"
    },
    {
      "positive": false,
      "regex": "^\\/(?:.+\\/)?[^\\/]*\\.[^\\/]*$"
    },
    {
      "positive": false,
      "regex": "^\\/(?:.+\\/)?[^\\/]*__[^\\/]*$"
    },
    {
      "positive": false,
      "regex": "^\\/(?:.+\\/)?[^\\/]*__[^\\/]*\\/.*$"
    }
  ]
}